mcp_ffmpeg_detector/__init__.py
mcp_ffmpeg_detector/ffmpeg_utils.py
mcp_ffmpeg_detector/server.py
mcp_ffmpeg_detector-1.0.0.dist-info/METADATA
mcp_ffmpeg_detector-1.0.0.dist-info/WHEEL
mcp_ffmpeg_detector-1.0.0.dist-info/entry_points.txt
mcp_ffmpeg_detector-1.0.0.dist-info/top_level.txt
mcp_ffmpeg_detector-1.0.0.dist-info/RECORD
