Metadata-Version: 2.4
Name: mcp-ffmpeg-detector
Version: 1.0.0
Summary: A simple MCP tool to detect and install FFmpeg
Author-email: Your Name <your.email@example.com>
License: MIT
Project-URL: Homepage, https://github.com/yourusername/mcp-ffmpeg-detector
Project-URL: Documentation, https://github.com/yourusername/mcp-ffmpeg-detector#readme
Project-URL: Repository, https://github.com/yourusername/mcp-ffmpeg-detector.git
Project-URL: Issues, https://github.com/yourusername/mcp-ffmpeg-detector/issues
Keywords: mcp,ffmpeg,detection,installation
Classifier: Development Status :: 4 - Beta
Classifier: Intended Audience :: Developers
Classifier: License :: OSI Approved :: MIT License
Classifier: Operating System :: OS Independent
Classifier: Programming Language :: Python :: 3
Classifier: Programming Language :: Python :: 3.8
Classifier: Programming Language :: Python :: 3.9
Classifier: Programming Language :: Python :: 3.10
Classifier: Programming Language :: Python :: 3.11
Classifier: Programming Language :: Python :: 3.12
Requires-Python: >=3.8
Requires-Dist: mcp>=0.2.0
Requires-Dist: imageio-ffmpeg>=0.4.0
